{"version":"1","source":"dists.dss","distributions":{"Q13a":{"columns":["value"],"weight_sets":["default"],"rows":[{"values":["special"],"weights":[20]},{"values":["pending"],"weights":[20]},{"values":["unusual"],"weights":[20]},{"values":["express"],"weights":[20]}]},"Q13b":{"columns":["value"],"weight_sets":["default"],"rows":[{"values":["packages"],"weights":[40]},{"values":["requests"],"weights":[40]},{"values":["accounts"],"weights":[40]},{"values":["deposits"],"weights":[40]}]},"adjectives":{"columns":["value"],"weight_sets":["default"],"rows":[{"values":["special"],"weights":[20]},{"values":["pending"],"weights":[20]},{"values":["unusual"],"weights":[20]},{"values":["express"],"weights":[20]},{"values":["furious"],"weights":[1]},{"values":["sly"],"weights":[1]},{"values":["careful"],"weights":[1]},{"values":["blithe"],"weights":[1]},{"values":["quick"],"weights":[1]},{"values":["fluffy"],"weights":[1]},{"values":["slow"],"weights":[1]},{"values":["quiet"],"weights":[1]},{"values":["ruthless"],"weights":[1]},{"values":["thin"],"weights":[1]},{"values":["close"],"weights":[1]},{"values":["dogged"],"weights":[1]},{"values":["daring"],"weights":[1]},{"values":["brave"],"weights":[1]},{"values":["stealthy"],"weights":[1]},{"values":["permanent"],"weights":[1]},{"values":["enticing"],"weights":[1]},{"values":["idle"],"weights":[1]},{"values":["busy"],"weights":[1]},{"values":["regular"],"weights":[50]},{"values":["final"],"weights":[40]},{"values":["ironic"],"weights":[40]},{"values":["even"],"weights":[30]},{"values":["bold"],"weights":[20]},{"values":["silent"],"weights":[10]}]},"adverbs":{"columns":["value"],"weight_sets":["default"],"rows":[{"values":["sometimes"],"weights":[1]},{"values":["always"],"weights":[1]},{"values":["never"],"weights":[1]},{"values":["furiously"],"weights":[50]},{"values":["slyly"],"weights":[50]},{"values":["carefully"],"weights":[50]},{"values":["blithely"],"weights":[40]},{"values":["quickly"],"weights":[30]},{"values":["fluffily"],"weights":[20]},{"values":["slowly"],"weights":[1]},{"values":["quietly"],"weights":[1]},{"values":["ruthlessly"],"weights":[1]},{"values":["thinly"],"weights":[1]},{"values":["closely"],"weights":[1]},{"values":["doggedly"],"weights":[1]},{"values":["daringly"],"weights":[1]},{"values":["bravely"],"weights":[1]},{"values":["stealthily"],"weights":[1]},{"values":["permanently"],"weights":[1]},{"values":["enticingly"],"weights":[1]},{"values":["idly"],"weights":[1]},{"values":["busily"],"weights":[1]},{"values":["regularly"],"weights":[1]},{"values":["finally"],"weights":[1]},{"values":["ironically"],"weights":[1]},{"values":["evenly"],"weights":[1]},{"values":["boldly"],"weights":[1]},{"values":["silently"],"weights":[1]}]},"articles":{"columns":["value"],"weight_sets":["default"],"rows":[{"values":["the"],"weights":[50]},{"values":["a"],"weights":[20]},{"values":["an"],"weights":[5]}]},"auxillaries":{"columns":["value"],"weight_sets":["default"],"rows":[{"values":["do"],"weights":[1]},{"values":["may"],"weights":[1]},{"values":["might"],"weights":[1]},{"values":["shall"],"weights":[1]},{"values":["will"],"weights":[1]},{"values":["would"],"weights":[1]},{"values":["can"],"weights":[1]},{"values":["could"],"weights":[1]},{"values":["should"],"weights":[1]},{"values":["ought to"],"weights":[1]},{"values":["must"],"weights":[1]},{"values":["will have to"],"weights":[1]},{"values":["shall have to"],"weights":[1]},{"values":["could have to"],"weights":[1]},{"values":["should have to"],"weights":[1]},{"values":["must have to"],"weights":[1]},{"values":["need to"],"weights":[1]},{"values":["try to"],"weights":[1]}]},"category":{"columns":["value"],"weight_sets":["default"],"rows":[{"values":["FURNITURE"],"weights":[1]},{"values":["STORAGE EQUIP"],"weights":[1]},{"values":["TOOLS"],"weights":[1]},{"values":["MACHINE TOOLS"],"weights":[1]},{"values":["OTHER"],"weights":[1]}]},"colors":{"columns":["value"],"weight_sets":["default"],"rows":[{"values":["almond"],"weights":[1]},{"values":["antique"],"weights":[1]},{"values":["aquamarine"],"weights":[1]},{"values":["azure"],"weights":[1]},{"values":["beige"],"weights":[1]},{"values":["bisque"],"weights":[1]},{"values":["black"],"weights":[1]},{"values":["blanched"],"weights":[1]},{"values":["blue"],"weights":[1]},{"values":["blush"],"weights":[1]},{"values":["brown"],"weights":[1]},{"values":["burlywood"],"weights":[1]},{"values":["burnished"],"weights":[1]},{"values":["chartreuse"],"weights":[1]},{"values":["chiffon"],"weights":[1]},{"values":["chocolate"],"weights":[1]},{"values":["coral"],"weights":[1]},{"values":["cornflower"],"weights":[1]},{"values":["cornsilk"],"weights":[1]},{"values":["cream"],"weights":[1]},{"values":["cyan"],"weights":[1]},{"values":["dark"],"weights":[1]},{"values":["deep"],"weights":[1]},{"values":["dim"],"weights":[1]},{"values":["dodger"],"weights":[1]},{"values":["drab"],"weights":[1]},{"values":["firebrick"],"weights":[1]},{"values":["floral"],"weights":[1]},{"values":["forest"],"weights":[1]},{"values":["frosted"],"weights":[1]},{"values":["gainsboro"],"weights":[1]},{"values":["ghost"],"weights":[1]},{"values":["goldenrod"],"weights":[1]},{"values":["green"],"weights":[1]},{"values":["grey"],"weights":[1]},{"values":["honeydew"],"weights":[1]},{"values":["hot"],"weights":[1]},{"values":["indian"],"weights":[1]},{"values":["ivory"],"weights":[1]},{"values":["khaki"],"weights":[1]},{"values":["lace"],"weights":[1]},{"values":["lavender"],"weights":[1]},{"values":["lawn"],"weights":[1]},{"values":["lemon"],"weights":[1]},{"values":["light"],"weights":[1]},{"values":["lime"],"weights":[1]},{"values":["linen"],"weights":[1]},{"values":["magenta"],"weights":[1]},{"values":["maroon"],"weights":[1]},{"values":["medium"],"weights":[1]},{"values":["metallic"],"weights":[1]},{"values":["midnight"],"weights":[1]},{"values":["mint"],"weights":[1]},{"values":["misty"],"weights":[1]},{"values":["moccasin"],"weights":[1]},{"values":["navajo"],"weights":[1]},{"values":["navy"],"weights":[1]},{"values":["olive"],"weights":[1]},{"values":["orange"],"weights":[1]},{"values":["orchid"],"weights":[1]},{"values":["pale"],"weights":[1]},{"values":["papaya"],"weights":[1]},{"values":["peach"],"weights":[1]},{"values":["peru"],"weights":[1]},{"values":["pink"],"weights":[1]},{"values":["plum"],"weights":[1]},{"values":["powder"],"weights":[1]},{"values":["puff"],"weights":[1]},{"values":["purple"],"weights":[1]},{"values":["red"],"weights":[1]},{"values":["rose"],"weights":[1]},{"values":["rosy"],"weights":[1]},{"values":["royal"],"weights":[1]},{"values":["saddle"],"weights":[1]},{"values":["salmon"],"weights":[1]},{"values":["sandy"],"weights":[1]},{"values":["seashell"],"weights":[1]},{"values":["sienna"],"weights":[1]},{"values":["sky"],"weights":[1]},{"values":["slate"],"weights":[1]},{"values":["smoke"],"weights":[1]},{"values":["snow"],"weights":[1]},{"values":["spring"],"weights":[1]},{"values":["steel"],"weights":[1]},{"values":["tan"],"weights":[1]},{"values":["thistle"],"weights":[1]},{"values":["tomato"],"weights":[1]},{"values":["turquoise"],"weights":[1]},{"values":["violet"],"weights":[1]},{"values":["wheat"],"weights":[1]},{"values":["white"],"weights":[1]},{"values":["yellow"],"weights":[1]}]},"grammar":{"columns":["value"],"weight_sets":["default"],"rows":[{"values":["N V T"],"weights":[3]},{"values":["N V P T"],"weights":[3]},{"values":["N V N T"],"weights":[3]},{"values":["N P V N T"],"weights":[1]},{"values":["N P V P T"],"weights":[1]}]},"instruct":{"columns":["value"],"weight_sets":["default"],"rows":[{"values":["DELIVER IN PERSON"],"weights":[1]},{"values":["COLLECT COD"],"weights":[1]},{"values":["TAKE BACK RETURN"],"weights":[1]},{"values":["NONE"],"weights":[1]}]},"msegmnt":{"columns":["value"],"weight_sets":["default"],"rows":[{"values":["AUTOMOBILE"],"weights":[1]},{"values":["BUILDING"],"weights":[1]},{"values":["FURNITURE"],"weights":[1]},{"values":["HOUSEHOLD"],"weights":[1]},{"values":["MACHINERY"],"weights":[1]}]},"nations":{"columns":["value"],"weight_sets":["default"],"rows":[{"values":["ALGERIA"],"weights":[0]},{"values":["ARGENTINA"],"weights":[1]},{"values":["BRAZIL"],"weights":[0]},{"values":["CANADA"],"weights":[0]},{"values":["EGYPT"],"weights":[3]},{"values":["ETHIOPIA"],"weights":[-4]},{"values":["FRANCE"],"weights":[3]},{"values":["GERMANY"],"weights":[0]},{"values":["INDIA"],"weights":[-1]},{"values":["INDONESIA"],"weights":[0]},{"values":["IRAN"],"weights":[2]},{"values":["IRAQ"],"weights":[0]},{"values":["JAPAN"],"weights":[-2]},{"values":["JORDAN"],"weights":[2]},{"values":["KENYA"],"weights":[-4]},{"values":["MOROCCO"],"weights":[0]},{"values":["MOZAMBIQUE"],"weights":[0]},{"values":["PERU"],"weights":[1]},{"values":["CHINA"],"weights":[1]},{"values":["ROMANIA"],"weights":[1]},{"values":["SAUDI ARABIA"],"weights":[1]},{"values":["VIETNAM"],"weights":[-2]},{"values":["RUSSIA"],"weights":[1]},{"values":["UNITED KINGDOM"],"weights":[0]},{"values":["UNITED STATES"],"weights":[-2]}]},"nations2":{"columns":["value"],"weight_sets":["default"],"rows":[{"values":["ALGERIA"],"weights":[1]},{"values":["ARGENTINA"],"weights":[1]},{"values":["BRAZIL"],"weights":[1]},{"values":["CANADA"],"weights":[1]},{"values":["EGYPT"],"weights":[1]},{"values":["ETHIOPIA"],"weights":[1]},{"values":["FRANCE"],"weights":[1]},{"values":["GERMANY"],"weights":[1]},{"values":["INDIA"],"weights":[1]},{"values":["INDONESIA"],"weights":[1]},{"values":["IRAN"],"weights":[1]},{"values":["IRAQ"],"weights":[1]},{"values":["JAPAN"],"weights":[1]},{"values":["JORDAN"],"weights":[1]},{"values":["KENYA"],"weights":[1]},{"values":["MOROCCO"],"weights":[1]},{"values":["MOZAMBIQUE"],"weights":[1]},{"values":["PERU"],"weights":[1]},{"values":["CHINA"],"weights":[1]},{"values":["ROMANIA"],"weights":[1]},{"values":["SAUDI ARABIA"],"weights":[1]},{"values":["VIETNAM"],"weights":[1]},{"values":["RUSSIA"],"weights":[1]},{"values":["UNITED KINGDOM"],"weights":[1]},{"values":["UNITED STATES"],"weights":[1]}]},"nouns":{"columns":["value"],"weight_sets":["default"],"rows":[{"values":["packages"],"weights":[40]},{"values":["requests"],"weights":[40]},{"values":["accounts"],"weights":[40]},{"values":["deposits"],"weights":[40]},{"values":["foxes"],"weights":[20]},{"values":["ideas"],"weights":[20]},{"values":["theodolites"],"weights":[20]},{"values":["pinto beans"],"weights":[20]},{"values":["instructions"],"weights":[20]},{"values":["dependencies"],"weights":[10]},{"values":["excuses"],"weights":[10]},{"values":["platelets"],"weights":[10]},{"values":["asymptotes"],"weights":[10]},{"values":["courts"],"weights":[5]},{"values":["dolphins"],"weights":[5]},{"values":["multipliers"],"weights":[1]},{"values":["sauternes"],"weights":[1]},{"values":["warthogs"],"weights":[1]},{"values":["frets"],"weights":[1]},{"values":["dinos"],"weights":[1]},{"values":["attainments"],"weights":[1]},{"values":["somas"],"weights":[1]},{"values":["Tiresias"],"weights":[1]},{"values":["patterns"],"weights":[1]},{"values":["forges"],"weights":[1]},{"values":["braids"],"weights":[1]},{"values":["frays"],"weights":[1]},{"values":["warhorses"],"weights":[1]},{"values":["dugouts"],"weights":[1]},{"values":["notornis"],"weights":[1]},{"values":["epitaphs"],"weights":[1]},{"values":["pearls"],"weights":[1]},{"values":["tithes"],"weights":[1]},{"values":["waters"],"weights":[1]},{"values":["orbits"],"weights":[1]},{"values":["gifts"],"weights":[1]},{"values":["sheaves"],"weights":[1]},{"values":["depths"],"weights":[1]},{"values":["sentiments"],"weights":[1]},{"values":["decoys"],"weights":[1]},{"values":["realms"],"weights":[1]},{"values":["pains"],"weights":[1]},{"values":["grouches"],"weights":[1]},{"values":["escapades"],"weights":[1]},{"values":["hockey players"],"weights":[1]}]},"np":{"columns":["value"],"weight_sets":["default"],"rows":[{"values":["N"],"weights":[10]},{"values":["J N"],"weights":[20]},{"values":["J, J N"],"weights":[10]},{"values":["D J N"],"weights":[50]}]},"o_oprio":{"columns":["value"],"weight_sets":["default"],"rows":[{"values":["1-URGENT"],"weights":[1]},{"values":["2-HIGH"],"weights":[1]},{"values":["3-MEDIUM"],"weights":[1]},{"values":["4-NOT SPECIFIED"],"weights":[1]},{"values":["5-LOW"],"weights":[1]}]},"p_cntr":{"columns":["value"],"weight_sets":["default"],"rows":[{"values":["SM CASE"],"weights":[1]},{"values":["SM BOX"],"weights":[1]},{"values":["SM BAG"],"weights":[1]},{"values":["SM JAR"],"weights":[1]},{"values":["SM PACK"],"weights":[1]},{"values":["SM PKG"],"weights":[1]},{"values":["SM CAN"],"weights":[1]},{"values":["SM DRUM"],"weights":[1]},{"values":["LG CASE"],"weights":[1]},{"values":["LG BOX"],"weights":[1]},{"values":["LG BAG"],"weights":[1]},{"values":["LG JAR"],"weights":[1]},{"values":["LG PACK"],"weights":[1]},{"values":["LG PKG"],"weights":[1]},{"values":["LG CAN"],"weights":[1]},{"values":["LG DRUM"],"weights":[1]},{"values":["MED CASE"],"weights":[1]},{"values":["MED BOX"],"weights":[1]},{"values":["MED BAG"],"weights":[1]},{"values":["MED JAR"],"weights":[1]},{"values":["MED PACK"],"weights":[1]},{"values":["MED PKG"],"weights":[1]},{"values":["MED CAN"],"weights":[1]},{"values":["MED DRUM"],"weights":[1]},{"values":["JUMBO CASE"],"weights":[1]},{"values":["JUMBO BOX"],"weights":[1]},{"values":["JUMBO BAG"],"weights":[1]},{"values":["JUMBO JAR"],"weights":[1]},{"values":["JUMBO PACK"],"weights":[1]},{"values":["JUMBO PKG"],"weights":[1]},{"values":["JUMBO CAN"],"weights":[1]},{"values":["JUMBO DRUM"],"weights":[1]},{"values":["WRAP CASE"],"weights":[1]},{"values":["WRAP BOX"],"weights":[1]},{"values":["WRAP BAG"],"weights":[1]},{"values":["WRAP JAR"],"weights":[1]},{"values":["WRAP PACK"],"weights":[1]},{"values":["WRAP PKG"],"weights":[1]},{"values":["WRAP CAN"],"weights":[1]},{"values":["WRAP DRUM"],"weights":[1]}]},"p_names":{"columns":["value"],"weight_sets":["default"],"rows":[{"values":["CLEANER"],"weights":[1]},{"values":["SOAP"],"weights":[1]},{"values":["DETERGENT"],"weights":[1]},{"values":["EXTRA"],"weights":[1]}]},"p_types":{"columns":["value"],"weight_sets":["default"],"rows":[{"values":["STANDARD ANODIZED TIN"],"weights":[1]},{"values":["STANDARD ANODIZED NICKEL"],"weights":[1]},{"values":["STANDARD ANODIZED BRASS"],"weights":[1]},{"values":["STANDARD ANODIZED STEEL"],"weights":[1]},{"values":["STANDARD ANODIZED COPPER"],"weights":[1]},{"values":["STANDARD BURNISHED TIN"],"weights":[1]},{"values":["STANDARD BURNISHED NICKEL"],"weights":[1]},{"values":["STANDARD BURNISHED BRASS"],"weights":[1]},{"values":["STANDARD BURNISHED STEEL"],"weights":[1]},{"values":["STANDARD BURNISHED COPPER"],"weights":[1]},{"values":["STANDARD PLATED TIN"],"weights":[1]},{"values":["STANDARD PLATED NICKEL"],"weights":[1]},{"values":["STANDARD PLATED BRASS"],"weights":[1]},{"values":["STANDARD PLATED STEEL"],"weights":[1]},{"values":["STANDARD PLATED COPPER"],"weights":[1]},{"values":["STANDARD POLISHED TIN"],"weights":[1]},{"values":["STANDARD POLISHED NICKEL"],"weights":[1]},{"values":["STANDARD POLISHED BRASS"],"weights":[1]},{"values":["STANDARD POLISHED STEEL"],"weights":[1]},{"values":["STANDARD POLISHED COPPER"],"weights":[1]},{"values":["STANDARD BRUSHED TIN"],"weights":[1]},{"values":["STANDARD BRUSHED NICKEL"],"weights":[1]},{"values":["STANDARD BRUSHED BRASS"],"weights":[1]},{"values":["STANDARD BRUSHED STEEL"],"weights":[1]},{"values":["STANDARD BRUSHED COPPER"],"weights":[1]},{"values":["SMALL ANODIZED TIN"],"weights":[1]},{"values":["SMALL ANODIZED NICKEL"],"weights":[1]},{"values":["SMALL ANODIZED BRASS"],"weights":[1]},{"values":["SMALL ANODIZED STEEL"],"weights":[1]},{"values":["SMALL ANODIZED COPPER"],"weights":[1]},{"values":["SMALL BURNISHED TIN"],"weights":[1]},{"values":["SMALL BURNISHED NICKEL"],"weights":[1]},{"values":["SMALL BURNISHED BRASS"],"weights":[1]},{"values":["SMALL BURNISHED STEEL"],"weights":[1]},{"values":["SMALL BURNISHED COPPER"],"weights":[1]},{"values":["SMALL PLATED TIN"],"weights":[1]},{"values":["SMALL PLATED NICKEL"],"weights":[1]},{"values":["SMALL PLATED BRASS"],"weights":[1]},{"values":["SMALL PLATED STEEL"],"weights":[1]},{"values":["SMALL PLATED COPPER"],"weights":[1]},{"values":["SMALL POLISHED TIN"],"weights":[1]},{"values":["SMALL POLISHED NICKEL"],"weights":[1]},{"values":["SMALL POLISHED BRASS"],"weights":[1]},{"values":["SMALL POLISHED STEEL"],"weights":[1]},{"values":["SMALL POLISHED COPPER"],"weights":[1]},{"values":["SMALL BRUSHED TIN"],"weights":[1]},{"values":["SMALL BRUSHED NICKEL"],"weights":[1]},{"values":["SMALL BRUSHED BRASS"],"weights":[1]},{"values":["SMALL BRUSHED STEEL"],"weights":[1]},{"values":["SMALL BRUSHED COPPER"],"weights":[1]},{"values":["MEDIUM ANODIZED TIN"],"weights":[1]},{"values":["MEDIUM ANODIZED NICKEL"],"weights":[1]},{"values":["MEDIUM ANODIZED BRASS"],"weights":[1]},{"values":["MEDIUM ANODIZED STEEL"],"weights":[1]},{"values":["MEDIUM ANODIZED COPPER"],"weights":[1]},{"values":["MEDIUM BURNISHED TIN"],"weights":[1]},{"values":["MEDIUM BURNISHED NICKEL"],"weights":[1]},{"values":["MEDIUM BURNISHED BRASS"],"weights":[1]},{"values":["MEDIUM BURNISHED STEEL"],"weights":[1]},{"values":["MEDIUM BURNISHED COPPER"],"weights":[1]},{"values":["MEDIUM PLATED TIN"],"weights":[1]},{"values":["MEDIUM PLATED NICKEL"],"weights":[1]},{"values":["MEDIUM PLATED BRASS"],"weights":[1]},{"values":["MEDIUM PLATED STEEL"],"weights":[1]},{"values":["MEDIUM PLATED COPPER"],"weights":[1]},{"values":["MEDIUM POLISHED TIN"],"weights":[1]},{"values":["MEDIUM POLISHED NICKEL"],"weights":[1]},{"values":["MEDIUM POLISHED BRASS"],"weights":[1]},{"values":["MEDIUM POLISHED STEEL"],"weights":[1]},{"values":["MEDIUM POLISHED COPPER"],"weights":[1]},{"values":["MEDIUM BRUSHED TIN"],"weights":[1]},{"values":["MEDIUM BRUSHED NICKEL"],"weights":[1]},{"values":["MEDIUM BRUSHED BRASS"],"weights":[1]},{"values":["MEDIUM BRUSHED STEEL"],"weights":[1]},{"values":["MEDIUM BRUSHED COPPER"],"weights":[1]},{"values":["LARGE ANODIZED TIN"],"weights":[1]},{"values":["LARGE ANODIZED NICKEL"],"weights":[1]},{"values":["LARGE ANODIZED BRASS"],"weights":[1]},{"values":["LARGE ANODIZED STEEL"],"weights":[1]},{"values":["LARGE ANODIZED COPPER"],"weights":[1]},{"values":["LARGE BURNISHED TIN"],"weights":[1]},{"values":["LARGE BURNISHED NICKEL"],"weights":[1]},{"values":["LARGE BURNISHED BRASS"],"weights":[1]},{"values":["LARGE BURNISHED STEEL"],"weights":[1]},{"values":["LARGE BURNISHED COPPER"],"weights":[1]},{"values":["LARGE PLATED TIN"],"weights":[1]},{"values":["LARGE PLATED NICKEL"],"weights":[1]},{"values":["LARGE PLATED BRASS"],"weights":[1]},{"values":["LARGE PLATED STEEL"],"weights":[1]},{"values":["LARGE PLATED COPPER"],"weights":[1]},{"values":["LARGE POLISHED TIN"],"weights":[1]},{"values":["LARGE POLISHED NICKEL"],"weights":[1]},{"values":["LARGE POLISHED BRASS"],"weights":[1]},{"values":["LARGE POLISHED STEEL"],"weights":[1]},{"values":["LARGE POLISHED COPPER"],"weights":[1]},{"values":["LARGE BRUSHED TIN"],"weights":[1]},{"values":["LARGE BRUSHED NICKEL"],"weights":[1]},{"values":["LARGE BRUSHED BRASS"],"weights":[1]},{"values":["LARGE BRUSHED STEEL"],"weights":[1]},{"values":["LARGE BRUSHED COPPER"],"weights":[1]},{"values":["ECONOMY ANODIZED TIN"],"weights":[1]},{"values":["ECONOMY ANODIZED NICKEL"],"weights":[1]},{"values":["ECONOMY ANODIZED BRASS"],"weights":[1]},{"values":["ECONOMY ANODIZED STEEL"],"weights":[1]},{"values":["ECONOMY ANODIZED COPPER"],"weights":[1]},{"values":["ECONOMY BURNISHED TIN"],"weights":[1]},{"values":["ECONOMY BURNISHED NICKEL"],"weights":[1]},{"values":["ECONOMY BURNISHED BRASS"],"weights":[1]},{"values":["ECONOMY BURNISHED STEEL"],"weights":[1]},{"values":["ECONOMY BURNISHED COPPER"],"weights":[1]},{"values":["ECONOMY PLATED TIN"],"weights":[1]},{"values":["ECONOMY PLATED NICKEL"],"weights":[1]},{"values":["ECONOMY PLATED BRASS"],"weights":[1]},{"values":["ECONOMY PLATED STEEL"],"weights":[1]},{"values":["ECONOMY PLATED COPPER"],"weights":[1]},{"values":["ECONOMY POLISHED TIN"],"weights":[1]},{"values":["ECONOMY POLISHED NICKEL"],"weights":[1]},{"values":["ECONOMY POLISHED BRASS"],"weights":[1]},{"values":["ECONOMY POLISHED STEEL"],"weights":[1]},{"values":["ECONOMY POLISHED COPPER"],"weights":[1]},{"values":["ECONOMY BRUSHED TIN"],"weights":[1]},{"values":["ECONOMY BRUSHED NICKEL"],"weights":[1]},{"values":["ECONOMY BRUSHED BRASS"],"weights":[1]},{"values":["ECONOMY BRUSHED STEEL"],"weights":[1]},{"values":["ECONOMY BRUSHED COPPER"],"weights":[1]},{"values":["PROMO ANODIZED TIN"],"weights":[1]},{"values":["PROMO ANODIZED NICKEL"],"weights":[1]},{"values":["PROMO ANODIZED BRASS"],"weights":[1]},{"values":["PROMO ANODIZED STEEL"],"weights":[1]},{"values":["PROMO ANODIZED COPPER"],"weights":[1]},{"values":["PROMO BURNISHED TIN"],"weights":[1]},{"values":["PROMO BURNISHED NICKEL"],"weights":[1]},{"values":["PROMO BURNISHED BRASS"],"weights":[1]},{"values":["PROMO BURNISHED STEEL"],"weights":[1]},{"values":["PROMO BURNISHED COPPER"],"weights":[1]},{"values":["PROMO PLATED TIN"],"weights":[1]},{"values":["PROMO PLATED NICKEL"],"weights":[1]},{"values":["PROMO PLATED BRASS"],"weights":[1]},{"values":["PROMO PLATED STEEL"],"weights":[1]},{"values":["PROMO PLATED COPPER"],"weights":[1]},{"values":["PROMO POLISHED TIN"],"weights":[1]},{"values":["PROMO POLISHED NICKEL"],"weights":[1]},{"values":["PROMO POLISHED BRASS"],"weights":[1]},{"values":["PROMO POLISHED STEEL"],"weights":[1]},{"values":["PROMO POLISHED COPPER"],"weights":[1]},{"values":["PROMO BRUSHED TIN"],"weights":[1]},{"values":["PROMO BRUSHED NICKEL"],"weights":[1]},{"values":["PROMO BRUSHED BRASS"],"weights":[1]},{"values":["PROMO BRUSHED STEEL"],"weights":[1]},{"values":["PROMO BRUSHED COPPER"],"weights":[1]}]},"prepositions":{"columns":["value"],"weight_sets":["default"],"rows":[{"values":["about"],"weights":[50]},{"values":["above"],"weights":[50]},{"values":["according to"],"weights":[50]},{"values":["across"],"weights":[50]},{"values":["after"],"weights":[50]},{"values":["against"],"weights":[40]},{"values":["along"],"weights":[40]},{"values":["alongside of"],"weights":[30]},{"values":["among"],"weights":[30]},{"values":["around"],"weights":[20]},{"values":["at"],"weights":[10]},{"values":["atop"],"weights":[1]},{"values":["before"],"weights":[1]},{"values":["behind"],"weights":[1]},{"values":["beneath"],"weights":[1]},{"values":["beside"],"weights":[1]},{"values":["besides"],"weights":[1]},{"values":["between"],"weights":[1]},{"values":["beyond"],"weights":[1]},{"values":["by"],"weights":[1]},{"values":["despite"],"weights":[1]},{"values":["during"],"weights":[1]},{"values":["except"],"weights":[1]},{"values":["for"],"weights":[1]},{"values":["from"],"weights":[1]},{"values":["in place of"],"weights":[1]},{"values":["inside"],"weights":[1]},{"values":["instead of"],"weights":[1]},{"values":["into"],"weights":[1]},{"values":["near"],"weights":[1]},{"values":["of"],"weights":[1]},{"values":["on"],"weights":[1]},{"values":["outside"],"weights":[1]},{"values":["over"],"weights":[1]},{"values":["past"],"weights":[1]},{"values":["since"],"weights":[1]},{"values":["through"],"weights":[1]},{"values":["throughout"],"weights":[1]},{"values":["to"],"weights":[1]},{"values":["toward"],"weights":[1]},{"values":["under"],"weights":[1]},{"values":["until"],"weights":[1]},{"values":["up"],"weights":[1]},{"values":["upon"],"weights":[1]},{"values":["whithout"],"weights":[1]},{"values":["with"],"weights":[1]},{"values":["within"],"weights":[1]}]},"regions":{"columns":["value"],"weight_sets":["default"],"rows":[{"values":["AFRICA"],"weights":[1]},{"values":["AMERICA"],"weights":[1]},{"values":["ASIA"],"weights":[1]},{"values":["EUROPE"],"weights":[1]},{"values":["MIDDLE EAST"],"weights":[1]}]},"rflag":{"columns":["value"],"weight_sets":["default"],"rows":[{"values":["R"],"weights":[1]},{"values":["A"],"weights":[1]}]},"smode":{"columns":["value"],"weight_sets":["default"],"rows":[{"values":["REG AIR"],"weights":[1]},{"values":["AIR"],"weights":[1]},{"values":["RAIL"],"weights":[1]},{"values":["TRUCK"],"weights":[1]},{"values":["MAIL"],"weights":[1]},{"values":["FOB"],"weights":[1]},{"values":["SHIP"],"weights":[1]}]},"terminators":{"columns":["value"],"weight_sets":["default"],"rows":[{"values":["."],"weights":[50]},{"values":[";"],"weights":[1]},{"values":[":"],"weights":[1]},{"values":["?"],"weights":[1]},{"values":["!"],"weights":[1]},{"values":["--"],"weights":[1]}]},"verbs":{"columns":["value"],"weight_sets":["default"],"rows":[{"values":["sleep"],"weights":[20]},{"values":["wake"],"weights":[20]},{"values":["are"],"weights":[20]},{"values":["cajole"],"weights":[20]},{"values":["haggle"],"weights":[20]},{"values":["nag"],"weights":[10]},{"values":["use"],"weights":[10]},{"values":["boost"],"weights":[10]},{"values":["affix"],"weights":[5]},{"values":["detect"],"weights":[5]},{"values":["integrate"],"weights":[5]},{"values":["maintain"],"weights":[1]},{"values":["nod"],"weights":[1]},{"values":["was"],"weights":[1]},{"values":["lose"],"weights":[1]},{"values":["sublate"],"weights":[1]},{"values":["solve"],"weights":[1]},{"values":["thrash"],"weights":[1]},{"values":["promise"],"weights":[1]},{"values":["engage"],"weights":[1]},{"values":["hinder"],"weights":[1]},{"values":["print"],"weights":[1]},{"values":["x-ray"],"weights":[1]},{"values":["breach"],"weights":[1]},{"values":["eat"],"weights":[1]},{"values":["grow"],"weights":[1]},{"values":["impress"],"weights":[1]},{"values":["mold"],"weights":[1]},{"values":["poach"],"weights":[1]},{"values":["serve"],"weights":[1]},{"values":["run"],"weights":[1]},{"values":["dazzle"],"weights":[1]},{"values":["snooze"],"weights":[1]},{"values":["doze"],"weights":[1]},{"values":["unwind"],"weights":[1]},{"values":["kindle"],"weights":[1]},{"values":["play"],"weights":[1]},{"values":["hang"],"weights":[1]},{"values":["believe"],"weights":[1]},{"values":["doubt"],"weights":[1]}]},"vp":{"columns":["value"],"weight_sets":["default"],"rows":[{"values":["V"],"weights":[30]},{"values":["X V"],"weights":[1]},{"values":["V D"],"weights":[40]},{"values":["X V D"],"weights":[1]}]}}}